README.md
setup.cfg
setup.py
FullContact_AIO.egg-info/PKG-INFO
FullContact_AIO.egg-info/SOURCES.txt
FullContact_AIO.egg-info/dependency_links.txt
FullContact_AIO.egg-info/not-zip-safe
FullContact_AIO.egg-info/requires.txt
FullContact_AIO.egg-info/top_level.txt
fullcontact_aio/__init__.py