Metadata-Version: 1.1
Name: FullContact-AIO
Version: 0.0.8
Summary: Simple Python interface for FullContact, using aiohttp
Home-page: https://github.com/nitanmarcel/fullcontact-aio
Author: Marcel Alexandru Nitan
Author-email: nitan.marcel@gmail.com
License: MIT
Platform: any
Classifier: Environment :: Web Environment
Classifier: Intended Audience :: Developers
Classifier: Operating System :: OS Independent
Classifier: Programming Language :: Python
Classifier: Programming Language :: Python :: 3.6
Classifier: Programming Language :: Python :: 3.7
Classifier: Topic :: Internet :: WWW/HTTP :: Dynamic Content
Classifier: Topic :: Software Development :: Libraries :: Python Modules
